lib310_lite/__init__.py
lib310_lite/bigquery/_functions.py
lib310_lite/bigquery/client.py
lib310_lite/bigquery/constants.py
lib310_lite/laser/laser.py
lib310_lite-0.1.1.dist-info/WHEEL
lib310_lite-0.1.1.dist-info/METADATA
lib310_lite-0.1.1.dist-info/RECORD
