Metadata-Version: 2.1
Name: lib310-lite
Version: 0.1.1
Summary: lib310 Lite Python Package
Keywords: biology,AI,genomics,bioinforma,machine learning,GAN
Author: 310
Author-email: info@310.ai
Maintainer: Saman Fekri
Maintainer-email: saman@310.ai
Requires-Python: >=3.8
Classifier: Programming Language :: Python :: 3
Classifier: Programming Language :: Python :: 3.8
Classifier: Programming Language :: Python :: 3.9
Classifier: Programming Language :: Python :: 3.10
Requires-Dist: bounded_pool_executor (>=0.0.0)
Requires-Dist: dask (>=2022.11.0)
Requires-Dist: dask-sql (>=2022.11.0)
Requires-Dist: db-dtypes (>=1.0.0)
Requires-Dist: distributed (>=2022.11.0)
Requires-Dist: gcsfs (>=2022.11.0)
Requires-Dist: google-cloud (>=0.34.0)
Requires-Dist: google-cloud-bigquery (>=3.2.0)
Requires-Dist: mysqlclient (>=2.0.0)
Requires-Dist: numpy (<1.23.0)
